pydotthz/__init__.py
pydotthz/pydotthz.py
pydotthz-1.0.1.dist-info/licenses/LICENSE.md
pydotthz-1.0.1.dist-info/METADATA
pydotthz-1.0.1.dist-info/WHEEL
pydotthz-1.0.1.dist-info/top_level.txt
pydotthz-1.0.1.dist-info/RECORD
