Metadata-Version: 2.4
Name: pydotthz
Version: 1.0.1
Summary: This Python Package allows interfacing with dotThz files.
Author-email: Linus Leo Stöckli <linus.stoeckli@unibe.ch>, Jasper Nelson Ward-Berry <jnw35@cam.ac.uk>
Project-URL: Homepage, https://github.com/dotTHzTAG/pydotthz
Project-URL: Bug Tracker, https://github.com/dotTHzTAG/pydotthz/issues
Classifier: Programming Language :: Python :: 3
Classifier: License :: OSI Approved :: MIT License
Classifier: Operating System :: OS Independent
Requires-Python: >=3.7
License-File: LICENSE.md
Requires-Dist: numpy
Requires-Dist: h5py
Dynamic: license-file
